<?xml version="1.0" encoding="UTF-8" standalone="no"?>
<!--iDempiere(r) Release 4.1_2016-10-31 -Smart Suite ERP, CRM and SCM- (c) 1999-2016 iDempiere(r); Implementation: iDempiere - Supported by iDempiere community--><!--<!DOCTYPE idempiereTrl PUBLIC "-//ComPiere, Inc.//DTD iDempiere Translation 1.0//EN" "http://www.idempiere.com/dtd/idempiereTrl.dtd">--><idempiereTrl language="zh_CN" table="M_Product">
 <row id="122" trl="Y">
  <value column="Name" original="Standard">标准数据</value>
  <value column="Description" original=""/>
  <value column="DocumentNote" original=""/>
 </row>
 <row id="123" trl="Y">
  <value column="Name" original="Oak Tree">橡树</value>
  <value column="Description" original=""/>
  <value column="DocumentNote" original="Oak Trees may grow quite a bit.">橡树可以培育得很多</value>
 </row>
 <row id="124" trl="Y">
  <value column="Name" original="Elm Tree">榆树</value>
  <value column="Description" original=""/>
  <value column="DocumentNote" original=""/>
 </row>
 <row id="125" trl="Y">
  <value column="Name" original="Grass Seed Container">草地种子容器</value>
  <value column="Description" original=""/>
  <value column="DocumentNote" original=""/>
 </row>
 <row id="126" trl="Y">
  <value column="Name" original="Planting Service">种植服务</value>
  <value column="Description" original=""/>
  <value column="DocumentNote" original=""/>
 </row>
 <row id="127" trl="Y">
  <value column="Name" original="Rose Bush">玫瑰花灌木丛</value>
  <value column="Description" original=""/>
  <value column="DocumentNote" original=""/>
 </row>
 <row id="128" trl="Y">
  <value column="Name" original="Azalea Bush">杜鹃花灌木丛</value>
  <value column="Description" original=""/>
  <value column="DocumentNote" original=""/>
 </row>
 <row id="129" trl="Y">
  <value column="Name" original="Holly Bush">冬青树灌木丛</value>
  <value column="Description" original=""/>
  <value column="DocumentNote" original=""/>
 </row>
 <row id="130" trl="Y">
  <value column="Name" original="Plum Tree">洋李树</value>
  <value column="Description" original=""/>
  <value column="DocumentNote" original=""/>
 </row>
 <row id="131" trl="Y">
  <value column="Name" original="Travel cost">差旅费用</value>
  <value column="Description" original="Travel related costs">差旅相关的成本</value>
  <value column="DocumentNote" original=""/>
 </row>
 <row id="132" trl="Y">
  <value column="Name" original="Mary Consultant">玛丽顾问</value>
  <value column="Description" original=""/>
  <value column="DocumentNote" original=""/>
 </row>
 <row id="133" trl="Y">
  <value column="Name" original="Patio Chair">户外椅</value>
  <value column="Description" original="Nice Chair for outdoors">户外使用的好椅子</value>
  <value column="DocumentNote" original=""/>
 </row>
 <row id="134" trl="Y">
  <value column="Name" original="Patio Table">户外桌</value>
  <value column="Description" original="Nice Table for outdoors">户外使用的好桌子</value>
  <value column="DocumentNote" original=""/>
 </row>
 <row id="135" trl="Y">
  <value column="Name" original="Patio Sun Screen">户外遮阳幕</value>
  <value column="Description" original="Protect from UV">防紫外线</value>
  <value column="DocumentNote" original=""/>
 </row>
 <row id="136" trl="Y">
  <value column="Name" original="Fertilizer #50">50号肥料</value>
  <value column="Description" original="50 # Bag of Lawn Fertilizer">草坪肥料 50# 袋装</value>
  <value column="DocumentNote" original=""/>
 </row>
 <row id="137" trl="Y">
  <value column="Name" original="Mulch 10#">10 号护根</value>
  <value column="Description" original="10# Bag of Mulch">护根 10# 袋装</value>
  <value column="DocumentNote" original=""/>
 </row>
 <row id="138" trl="Y">
  <value column="Name" original="Hoe 4 ft">4 英寸锄头</value>
  <value column="Description" original="4 Foot Metal Hoe">4 英寸的金属锄头</value>
  <value column="DocumentNote" original=""/>
 </row>
 <row id="139" trl="Y">
  <value column="Name" original="Rake Bamboo">竹耙</value>
  <value column="Description" original="4 Foot Bamboo Rake">4 英寸的竹耙</value>
  <value column="DocumentNote" original=""/>
 </row>
 <row id="140" trl="Y">
  <value column="Name" original="Rake Metal">金属耙</value>
  <value column="Description" original="4 Foot Metal Rake">4 英寸的金属耙</value>
  <value column="DocumentNote" original=""/>
 </row>
 <row id="141" trl="Y">
  <value column="Name" original="Weeder">除草机</value>
  <value column="Description" original="Hand Weeder">人力除草机</value>
  <value column="DocumentNote" original=""/>
 </row>
 <row id="142" trl="Y">
  <value column="Name" original="Transplanter">移植机</value>
  <value column="Description" original="Hand Transplanter">人力移植机</value>
  <value column="DocumentNote" original=""/>
 </row>
 <row id="143" trl="Y">
  <value column="Name" original="Grass Seeder">草地播种机</value>
  <value column="Description" original="Manual Grass Seeder">人工草地播种机</value>
  <value column="DocumentNote" original=""/>
 </row>
 <row id="144" trl="Y">
  <value column="Name" original="Lawn Tiller">草坪修剪机</value>
  <value column="Description" original="Manual Lawn Tiller">人工草坪修剪机</value>
  <value column="DocumentNote" original=""/>
 </row>
 <row id="145" trl="Y">
  <value column="Name" original="Patio Furniture Set">户外装饰套件</value>
  <value column="Description" original="1 table, 4 Chairs and 1 Sun Screen">1 个桌子, 4 把椅子和 1 块遮阳幕</value>
  <value column="DocumentNote" original="&#9;">	</value>
 </row>
 <row id="146" trl="Y">
  <value column="Name" original="How To Plant">如何种植</value>
  <value column="Description" original="Information on how to best to plant your future.">最佳种植计划</value>
  <value column="DocumentNote" original=""/>
 </row>
 <row id="147" trl="Y">
  <value column="Name" original="TShirt - Red Large">T恤 - 红色大号</value>
  <value column="Description" original=""/>
  <value column="DocumentNote" original=""/>
 </row>
 <row id="148" trl="Y">
  <value column="Name" original="TShirt - Green Large">T恤 - 绿色大号</value>
  <value column="Description" original=""/>
  <value column="DocumentNote" original=""/>
 </row>
 <row id="50000" trl="Y">
  <value column="Name" original="Assembly Back Leg">后部装配</value>
  <value column="Description" original=""/>
  <value column="DocumentNote" original=""/>
 </row>
 <row id="50001" trl="Y">
  <value column="Name" original="Assembly Front Leg">前部装配</value>
  <value column="Description" original=""/>
  <value column="DocumentNote" original=""/>
 </row>
 <row id="50002" trl="Y">
  <value column="Name" original="#6-32 x 3/8 Socket Head Cap Screw">#6-32 x 3/8    六角螺丝刀</value>
  <value column="Description" original=""/>
  <value column="DocumentNote" original=""/>
 </row>
 <row id="50003" trl="Y">
  <value column="Name" original="Ultra Glue">强力胶水</value>
  <value column="Description" original=""/>
  <value column="DocumentNote" original=""/>
 </row>
 <row id="50004" trl="Y">
  <value column="Name" original="Seat">座位</value>
  <value column="Description" original=""/>
  <value column="DocumentNote" original=""/>
 </row>
 <row id="50005" trl="Y">
  <value column="Name" original="Back Support">支持</value>
  <value column="Description" original=""/>
  <value column="DocumentNote" original=""/>
 </row>
 <row id="50007" trl="Y">
  <value column="Name" original="Fertilizer #70">70号化肥</value>
  <value column="Description" original="70 # Bag of Lawn Fertilizer">70#包装草坪化肥</value>
  <value column="DocumentNote" original=""/>
 </row>
 <row id="50008" trl="Y">
  <value column="Name" original="Lawn Fertilizer">草坪化肥</value>
  <value column="Description" original=""/>
  <value column="DocumentNote" original=""/>
 </row>
 <row id="50009" trl="Y">
  <value column="Name" original="Nitrogen">氮</value>
  <value column="Description" original=""/>
  <value column="DocumentNote" original=""/>
 </row>
 <row id="50010" trl="Y">
  <value column="Name" original="Phosphorus">磷</value>
  <value column="Description" original=""/>
  <value column="DocumentNote" original=""/>
 </row>
 <row id="50012" trl="Y">
  <value column="Name" original="Potassium">钾</value>
  <value column="Description" original=""/>
  <value column="DocumentNote" original=""/>
 </row>
 <row id="50013" trl="Y">
  <value column="Name" original="Bag 50 Kg">50Kg 包装</value>
  <value column="Description" original=""/>
  <value column="DocumentNote" original=""/>
 </row>
 <row id="50014" trl="Y">
  <value column="Name" original="Bag 70 Kg">70Kg 包装</value>
  <value column="Description" original=""/>
  <value column="DocumentNote" original=""/>
 </row>
 <row id="50015" trl="Y">
  <value column="Name" original="Front Leg">前腿</value>
  <value column="Description" original=""/>
  <value column="DocumentNote" original=""/>
 </row>
 <row id="50016" trl="Y">
  <value column="Name" original="Back Leg">后腿</value>
  <value column="Description" original=""/>
  <value column="DocumentNote" original=""/>
 </row>
 <row id="50017" trl="Y">
  <value column="Name" original="Water">水</value>
  <value column="Description" original=""/>
  <value column="DocumentNote" original=""/>
 </row>
 <row id="50018" trl="Y">
  <value column="Name" original="Fertilizer Plant">化肥厂</value>
  <value column="Description" original=""/>
  <value column="DocumentNote" original=""/>
 </row>
 <row id="50019" trl="Y">
  <value column="Name" original="Assembly Area">装配区域</value>
  <value column="Description" original=""/>
  <value column="DocumentNote" original=""/>
 </row>
 <row id="50020" trl="Y">
  <value column="Name" original="Paint Area">打印区</value>
  <value column="Description" original=""/>
  <value column="DocumentNote" original=""/>
 </row>
 <row id="50021" trl="Y">
  <value column="Name" original="Chrome Subcontract Area">分包区域</value>
  <value column="Description" original=""/>
  <value column="DocumentNote" original=""/>
 </row>
 <row id="50022" trl="Y">
  <value column="Name" original="Inspection Area">兴趣领域</value>
  <value column="Description" original=""/>
  <value column="DocumentNote" original=""/>
 </row>
 <row id="50023" trl="Y">
  <value column="Name" original="Furniture Plant">家具厂</value>
  <value column="Description" original=""/>
  <value column="DocumentNote" original=""/>
 </row>
 <row id="50024" trl="Y">
  <value column="Name" original="Packing Production Line">生产领料行</value>
  <value column="Description" original=""/>
  <value column="DocumentNote" original=""/>
 </row>
 <row id="50025" trl="Y">
  <value column="Name" original="Mixed Area">混合区域</value>
  <value column="Description" original=""/>
  <value column="DocumentNote" original=""/>
 </row>
 <row id="50026" trl="Y">
  <value column="Name" original="Dry Area">干燥区域</value>
  <value column="Description" original=""/>
  <value column="DocumentNote" original=""/>
 </row>
 <row id="50027" trl="Y">
  <value column="Name" original="Fertilizer Inspection Area">肥料检验区域</value>
  <value column="Description" original=""/>
  <value column="DocumentNote" original=""/>
 </row>
 <row trl="N" uuid="1029ebcc-c39d-4ec0-89c6-0b187bad8856">
  <value column="Name" original="aaaaaaaaaa">aaaaaaaaaa</value>
  <value column="Description" original=""/>
  <value column="DocumentNote" original=""/>
 </row>
 <row trl="N" uuid="6ced6fca-cc6e-4817-99c5-d0081c5dc817">
  <value column="Name" original="Fertilizer 100#">Fertilizer 100#</value>
  <value column="Description" original=""/>
  <value column="DocumentNote" original=""/>
 </row>
</idempiereTrl>
